[
  { "name": "Carissa Moore",            "country": "USA" },
  { "name": "Tyler Wright",             "country": "AUS" },
  { "name": "Caroline Marks",           "country": "USA" },
  { "name": "Molly Picklum",            "country": "AUS" },
  { "name": "Bettylou Sakura Johnson",  "country": "USA" },
  { "name": "Caitlin Simmers",          "country": "USA" },
  { "name": "Tatiana Weston-Webb",      "country": "BRA" },
  { "name": "Brisa Hennessy",           "country": "CRI" },
  { "name": "Isabella Nichols",         "country": "AUS" },
  { "name": "Johanne Defay",            "country": "FRA" },
  { "name": "Sally Fitzgibbons",        "country": "AUS" },
  { "name": "Lakey Peterson",           "country": "USA" },
  { "name": "Gabriela Bryan",           "country": "USA" },
  { "name": "Luana Silva",              "country": "USA" },
  { "name": "Malia Manuel",             "country": "USA" },
  { "name": "Daniella Rosas",           "country": "PER" },
  { "name": "Sofia Mulanovich",         "country": "PER" },
  { "name": "Dimity Stoyle",            "country": "AUS" },
  { "name": "Stephanie Gilmore",        "country": "AUS" },
  { "name": "Erin Brooks",              "country": "CAN" }
]
